pcdf.cp38-win_amd64.pyd
pcdf-0.1.0.dist-info/METADATA
pcdf-0.1.0.dist-info/WHEEL
pcdf-0.1.0.dist-info/top_level.txt
pcdf-0.1.0.dist-info/RECORD
