Metadata-Version: 2.1
Name: pcdf
Version: 0.1.0
Summary: pcdf
Home-page: UNKNOWN
Author: UNKNOWN
Author-email: UNKNOWN
License: Licence
Keywords: pcdf
Platform: any
